local_lambda/__init__.py
local_lambda/cli.py
local_lambda/mocks.py
local_lambda/runtime.py
local_aws_lambda-0.1.4.dist-info/LICENSE
local_aws_lambda-0.1.4.dist-info/METADATA
local_aws_lambda-0.1.4.dist-info/WHEEL
local_aws_lambda-0.1.4.dist-info/entry_points.txt
local_aws_lambda-0.1.4.dist-info/top_level.txt
local_aws_lambda-0.1.4.dist-info/RECORD
