Metadata-Version: 2.2
Name: local-aws-lambda
Version: 0.1.4
Summary: Local AWS Lambda is a Python package that allows you to simulate AWS Lambda functions in your local development environment. This helps you test and debug your serverless applications without deploying them to AWS.
Author-email: Aswath <aswathrachuru@gmail.com>
Project-URL: Homepage, https://github.com/ashwath1295/local-aws-lambda
Project-URL: Bug Tracker, https://github.com/ashwath1295/local-aws-lambda/issues
Requires-Python: >=3.7
License-File: LICENSE
